cns_nanoprometheus_client/__init__.py
cns_nanoprometheus_client/aggregator.py
cns_nanoprometheus_client/client.py
cns_nanoprometheus_client/config.py
cns_nanoprometheus_client/exceptions.py
cns_nanoprometheus_client/logging_config.py
cns_nanoprometheus_client/metrics.py
cns_nanoprometheus_client/safe_metrics.py
cns_nanoprometheus_client-0.5.18.dist-info/LICENSE
cns_nanoprometheus_client-0.5.18.dist-info/METADATA
cns_nanoprometheus_client-0.5.18.dist-info/WHEEL
cns_nanoprometheus_client-0.5.18.dist-info/entry_points.txt
cns_nanoprometheus_client-0.5.18.dist-info/top_level.txt
cns_nanoprometheus_client-0.5.18.dist-info/RECORD
